{
  "cycle": 8,
  "timestamp": "20260528_204239",
  "phases": {
    "bootstrap": {
      "success": true,
      "output": "Here's the comprehensive codebase health report:\n\n\u2550\u2550\u2550\u2550\u2550\u2550\u2550\u2550\u2550\u2550\u2550\u2550\u2550\u2550\u2550\u2550\u2550\u2550\u2550\u2550\u2550\u2550\u2550\u2550\u2550\u2550\u2550\u2550\u2550\u2550\u2550\u2550\u2550\u2550\u2550\u2550\u2550\u2550\u2550\u2550\u2550\u2550\u2550\u2550\u2550\u2550\n  APEX AUTOPILOT ENGINE \u2014 Codebase Health Check\n\u2550\u2550\u2550\u2550\u2550\u2550\u2550\u2550\u2550\u2550\u2550\u2550\u2550\u2550\u2550\u2550\u2550\u2550\u2550\u2550\u2550\u2550\u2550\u2550\u2550\u2550\u2550\u2550\u2550\u2550\u2550\u2550\u2550\u2550\u2550\u2550\u2550\u2550\u2550\u2550\u2550\u2550\u2550\u2550\u2550\u2550\n\n\ud83d\udfe2 PYTHON ENVIRONMENT (PASS)\n   Python 3.13.12 via miniconda (base)\n   .venv at project root \u2014 activated, 260 packages installed\n   uv 0.9.21 available as alternative package manager\n   No broken dependencies (pip check passes)\n\n\ud83d\udfe2 PROJECT STRUCTURE (PASS)\n   95+ Python source files across 15+ packages\n   L0"
    },
    "analyze": {
      "success": true,
      "output": "error: unknown option '--dir'\n\nTry 'copilot --help' for more information.\n"
    },
    "plan": {
      "success": true,
      "output": "Now I have a thorough picture of the project. Let me compile the improvement tasks.\n\nBased on codebase analysis, here are the top 10 improvement tasks for APEX Autopilot:\n\n---\n\n## Improvement Tasks (Max 10)\n\n### 1. Fix yfinance 404 Error Spam in Ingestion\n**File:** `src/apex/layers/l0/ingestion.py`\n**Problem:** Symbols like SMH, SOXX, XSD, and SPY consistently return `HTTP Error 404` from yfinance when fetching fundamentals data. The broad `except Exception` at line 102 silently swallows the err"
    },
    "execute": {
      "success": true,
      "output": "flags provided but not defined: -workdir\nUsage of agy:\n  --add-dir                       Add a directory to the workspace (repeatable) (default [])\n  -c                              Short alias for --continue\n  --continue                      Continue the most recent conversation\n  --conversation                  Resume a previous conversation by ID\n  --dangerously-skip-permissions  Auto-approve all tool permission requests without prompting\n  -i                              Short alias for --pr"
    },
    "test": {
      "success": true,
      "output": "**Test Suite Results: 346 passed, 1 skipped, 0 failures** (112.9s)\n\nAll tests green. The recent fix commits on this branch are holding up:\n\n| Area | Recent Fixes |\n|---|---|\n| **Security** | Code injection vector eliminated (`42ee58f`), silent exception swallows replaced with logging (`0ee555c`) |\n| **Linting/Imports** | Unused imports removed (`af3d9c1`), missing `__init__.py` files added (`1f73430`), bare excepts replaced (`c614b17`) |\n| **Type safety** | TS2531 null safety errors in arb-radar"
    },
    "commit": {
      "success": true,
      "output": "Committed as `a0df353` on `main`:\n\n```\nfix: anchor data/ ignore pattern to repo root in .gcloudignore\n```\n\nSingle change: `data/` \u2192 `/data/` in `.gcloudignore` so the ignore rule only applies to the top-level `data/` directory, not any nested `data/` folders.\n"
    },
    "report": {
      "success": true,
      "output": "error: unknown option '--dir'\n\nTry 'copilot --help' for more information.\n"
    }
  }
}